LICENSE.txt
MANIFEST.in
README.rst
setup.cfg
setup.py
SinaWeibo/__init__.py
SinaWeibo/blog.py
SinaWeibo/fans.py
SinaWeibo/follow.py
SinaWeibo/utils.py
SinaWeibo/weibo.py
sinaweibo.egg-info/PKG-INFO
sinaweibo.egg-info/SOURCES.txt
sinaweibo.egg-info/dependency_links.txt
sinaweibo.egg-info/requires.txt
sinaweibo.egg-info/top_level.txt
sinaweibo.egg-info/zip-safe
test/test.py
test/testWx.py